dagio/__init__.py
dagio/depends_decorator.py
dagio/run_async_decorator.py
dagio-0.0.2.dist-info/LICENSE
dagio-0.0.2.dist-info/METADATA
dagio-0.0.2.dist-info/WHEEL
dagio-0.0.2.dist-info/top_level.txt
dagio-0.0.2.dist-info/RECORD
