Metadata-Version: 2.1
Name: dagio
Version: 0.0.2
Summary: A python package for running directed acyclic graphs of asynchronous I/O operations
Home-page: https://github.com/brendanhasz/dagio
Author: Brendan Hasz
Author-email: winsto99@gmail.com
License: MIT
Platform: UNKNOWN
Classifier: Programming Language :: Python :: 3
Classifier: License :: OSI Approved :: MIT License
Classifier: Operating System :: OS Independent
Classifier: Development Status :: 3 - Alpha
License-File: LICENSE
Provides-Extra: dev
Requires-Dist: autoflake (>=1.4) ; extra == 'dev'
Requires-Dist: black (>=19.10b0) ; extra == 'dev'
Requires-Dist: bumpversion ; extra == 'dev'
Requires-Dist: flake8 (>=3.8.3) ; extra == 'dev'
Requires-Dist: isort (>=5.1.2) ; extra == 'dev'
Requires-Dist: pytest (>=6.0.0rc1) ; extra == 'dev'
Requires-Dist: pytest-asyncio (>=0.15.1) ; extra == 'dev'
Requires-Dist: pytest-cov (>=2.7.1) ; extra == 'dev'
Requires-Dist: setuptools (>=49.1.0) ; extra == 'dev'
Requires-Dist: twine (>=3.2.0) ; extra == 'dev'
Requires-Dist: wheel (>=0.34.2) ; extra == 'dev'
